mdinfo/__init__.py
mdinfo/__main__.py
mdinfo/_version.py
mdinfo/cli.py
mdinfo/constants.py
mdinfo/datetime_formatter.py
mdinfo/datetime_utils.py
mdinfo/filetemplate.md
mdinfo/filetemplate.py
mdinfo/hookspecs.py
mdinfo/mdinfo.py
mdinfo/mtlparser.py
mdinfo/mtlparser.tx
mdinfo/path_utils.py
mdinfo/plugins/__init__.py
mdinfo/plugins/templates/__init__.py
mdinfo/plugins/templates/audio.py
mdinfo/plugins/templates/docx.py
mdinfo/plugins/templates/filedates.py
mdinfo/plugins/templates/filepath.py
mdinfo/plugins/templates/filestat.py
mdinfo/plugins/templates/pdf.py
mdinfo/renderoptions.py
mdinfo/utils.py
mdinfo-0.2.0.dist-info/LICENSE
mdinfo-0.2.0.dist-info/METADATA
mdinfo-0.2.0.dist-info/WHEEL
mdinfo-0.2.0.dist-info/entry_points.txt
mdinfo-0.2.0.dist-info/RECORD
