Metadata-Version: 2.1
Name: mdinfo
Version: 0.2.0
Summary: Print file metadata in various formats using a metadata template system.
License: MIT
Author: Rhet Turnbull
Author-email: rturnbull+git@gmail.com
Requires-Python: >=3.9,<3.14
Classifier: License :: OSI Approved :: MIT License
Classifier: Programming Language :: Python :: 3
Classifier: Programming Language :: Python :: 3.9
Classifier: Programming Language :: Python :: 3.10
Classifier: Programming Language :: Python :: 3.11
Classifier: Programming Language :: Python :: 3.12
Classifier: Programming Language :: Python :: 3.13
Requires-Dist: click (>=8.1.3,<9.0.0)
Requires-Dist: cloup (>=2.0.0.post1,<3.0.0)
Requires-Dist: datetime-tzutils (>=1.0.1,<2.0.0)
Requires-Dist: pathvalidate (>=2.5.2,<3.0.0)
Requires-Dist: pdfminer.six (>=20221105,<20221106)
Requires-Dist: pluggy (>=1.0.0,<2.0.0)
Requires-Dist: python-docx (>=0.8.11,<0.9.0)
Requires-Dist: rich (>=13.3.1,<14.0.0)
Requires-Dist: textX (>=4.0.1,<5.0.0)
Requires-Dist: tinytag (>=1.8.1,<2.0.0)
